{
    "@odata.id": "/redfish/v1/Systems/system/LogServices/ALL/Entries/302",
    "@odata.type": "#LogEntry.v1_8_0.LogEntry",
    "Created": "2024-03-14T18:44:26+00:00",
    "EntryCode": "Deassert",
    "EntryType": "SEL",
    "EventId": "302",
    "EventTimestamp": "2024-03-14T18:44:26+00:00",
    "GeneratorId": "0x0020",
    "Id": "302",
    "Message": "Upper Non-critical - going high - Deasserted",
    "MessageId": "0x8157133D",
    "Name": "ProcessorModule_0_CPU_1_TempAvg_0",
    "SensorNumber": 34,
    "SensorType": "Temperature",
    "Severity": "OK"
}