{
    "@odata.context": "/redfish/v1/$metadata#LogEntry.LogEntry",
    "@odata.etag": "\"1712249927\"",
    "@odata.id": "/redfish/v1/Managers/Self/LogServices/SEL/Entries/816",
    "@odata.type": "#LogEntry.v1_4_3.LogEntry",
    "Created": "2022-01-01T00:00:30+00:00",
    "Description": "SEL 895",
    "EntryCode": "Assert",
    "EntryType": "SEL",
    "EventTimestamp": "2022-01-01T00:00:12+00:00",
    "Id": "816",
    "Links": {
        "OriginOfCondition": {
            "@odata.id": "/redfish/v1/Systems/Self"
        }
    },
    "Message": "Event_Data_1 : 0, Record_Type : system event record, Sensor_Number : 241, Sensor_Name : ACPI_State, Event_Dir : Assertion event, Event_Data_2 : 255, Timestamp : 2022-01-01T00:00:12+00:00, EvM_Rev : IPMI v2.0 Event Messages, Generator_ID : 0x2000, Event_Data_3 : 255, Event_Type : S0/G0 'Working, Record_ID : 895, Sensor_Type : System ACPI PowerState, ",
    "MessageId": "0x00FFFF",
    "Name": "SEL 895",
    "SensorNumber": 241,
    "SensorType": "System ACPI PowerState",
    "Severity": "OK"
}