{
    "@odata.id": "/redfish/v1/Systems/system/LogServices/PostCodes/Entries/B21-20",
    "@odata.type": "#LogEntry.v1_12_0.LogEntry",
    "AdditionalDataURI": "/redfish/v1/Systems/system/LogServices/PostCodes/Entries/B21-20/attachment",
    "Created": "2024-01-05T14:44:31+00:00",
    "EntryType": "Event",
    "Id": "B21-20",
    "Message": "Boot Count: 21; Time Stamp Offset: 8.9967 seconds; POST Code: 0x01000000000002c100",
    "MessageArgs": [
        "21",
        "8.9967",
        "0x01000000000002c100"
    ],
    "MessageId": "OpenBMC.0.2.BIOSPOSTCode",
    "Name": "POST Code Log Entry",
    "Severity": "OK"
}