{
    "@odata.id": "/redfish/v1/Systems/system/LogServices/PostCodes/Entries/B24-47",
    "@odata.type": "#LogEntry.v1_12_0.LogEntry",
    "AdditionalDataURI": "/redfish/v1/Systems/system/LogServices/PostCodes/Entries/B24-47/attachment",
    "Created": "2024-01-26T22:09:36+00:00",
    "EntryType": "Event",
    "Id": "B24-47",
    "Message": "Boot Count: 24; Time Stamp Offset: 35.4029 seconds; POST Code: 0x010000000000010200",
    "MessageArgs": [
        "24",
        "35.4029",
        "0x010000000000010200"
    ],
    "MessageId": "OpenBMC.0.2.BIOSPOSTCode",
    "Name": "POST Code Log Entry",
    "Severity": "OK"
}