{
    "@odata.id": "/redfish/v1/Systems/system/LogServices/ALL/Entries/62",
    "@odata.type": "#LogEntry.v1_8_0.LogEntry",
    "Created": "2024-02-26T15:51:09+00:00",
    "EntryCode": "Deassert",
    "EntryType": "SEL",
    "EventId": "62",
    "EventTimestamp": "2024-02-26T15:51:09+00:00",
    "GeneratorId": "0x0020",
    "Id": "62",
    "Message": "Lower Non-critical - going high - Deasserted",
    "MessageId": "0x8101FFFF",
    "Name": "FAN_3_A_STATUS",
    "SensorNumber": 87,
    "SensorType": "Fan",
    "Severity": "OK"
}