{
    "@odata.id": "/redfish/v1/Systems/system/LogServices/PostCodes/Entries/B45-40",
    "@odata.type": "#LogEntry.v1_12_0.LogEntry",
    "AdditionalDataURI": "/redfish/v1/Systems/system/LogServices/PostCodes/Entries/B45-40/attachment",
    "Created": "2023-10-24T06:59:58+00:00",
    "EntryType": "Event",
    "Id": "B45-40",
    "Message": "Boot Count: 45; Time Stamp Offset: 9.1771 seconds; POST Code: 0x01000000000002c100",
    "MessageArgs": [
        "45",
        "9.1771",
        "0x01000000000002c100"
    ],
    "MessageId": "OpenBMC.0.2.BIOSPOSTCode",
    "Name": "POST Code Log Entry",
    "Severity": "OK"
}