{
    "@odata.id": "/redfish/v1/Systems/system/LogServices/PostCodes/Entries",
    "@odata.type": "#LogEntry.v1_4_0.LogEntry",
    "Description": "Collection of POST Code Log Entries",
    "Members": [
        {
            "@odata.id": "/redfish/v1/Systems/system/LogServices/PostCodes/Entries/B5-402",
            "@odata.type": "#LogEntry.v1_4_0.LogEntry",
            "Created": "2022-02-07T16:05:26+00:00",
            "EntryType": "Event",
            "Id": "B5-402",
            "Message": "Boot Count: 5: TS Offset: 207.5422; POST Code: 0xee",
            "MessageArgs": [
                "5",
                "207.5422",
                "0xee"
            ],
            "MessageId": "OpenBMC.0.1.BIOSPOSTCode",
            "Name": "POST Code Log Entry",
            "Severity": "OK"
        }
    ],
    "Members@odata.count": 1,
    "Name": "BIOS POST Code Log Entries"
}