{
    "@odata.id": "/redfish/v1/Systems/system/LogServices/PostCodes/Entries/B5-58",
    "@odata.type": "#LogEntry.v1_12_0.LogEntry",
    "AdditionalDataURI": "/redfish/v1/Systems/system/LogServices/PostCodes/Entries/B5-58/attachment",
    "Created": "2024-02-14T18:32:56+00:00",
    "EntryType": "Event",
    "Id": "B5-58",
    "Message": "Boot Count: 5; Time Stamp Offset: 38.4023 seconds; POST Code: 0x010000000000020200",
    "MessageArgs": [
        "5",
        "38.4023",
        "0x010000000000020200"
    ],
    "MessageId": "OpenBMC.0.2.BIOSPOSTCode",
    "Name": "POST Code Log Entry",
    "Severity": "OK"
}