{
    "@odata.id": "/redfish/v1/Systems/system/LogServices/ALL/Entries/347",
    "@odata.type": "#LogEntry.v1_8_0.LogEntry",
    "Created": "2024-04-03T17:35:28+00:00",
    "EntryCode": "Deassert",
    "EntryType": "SEL",
    "EventId": "347",
    "EventTimestamp": "2024-04-03T17:35:28+00:00",
    "GeneratorId": "0x0020",
    "Id": "347",
    "Message": "Drive Presence - Deasserted",
    "MessageId": "0xEF00FFFF",
    "Name": "DISK2_STATUS",
    "SensorNumber": 91,
    "SensorType": "Drive Slot/Bay",
    "Severity": "OK"
}