{
    "@odata.id": "/redfish/v1/Systems/system/LogServices/PostCodes/Entries/B25-26",
    "@odata.type": "#LogEntry.v1_12_0.LogEntry",
    "AdditionalDataURI": "/redfish/v1/Systems/system/LogServices/PostCodes/Entries/B25-26/attachment",
    "Created": "2023-11-27T17:24:22+00:00",
    "EntryType": "Event",
    "Id": "B25-26",
    "Message": "Boot Count: 25; Time Stamp Offset: 3.2993 seconds; POST Code: 0x010000000600020200",
    "MessageArgs": [
        "25",
        "3.2993",
        "0x010000000600020200"
    ],
    "MessageId": "OpenBMC.0.2.BIOSPOSTCode",
    "Name": "POST Code Log Entry",
    "Severity": "OK"
}