{
    "@odata.etag": "W/\"1712239920\"",
    "@odata.id": "/redfish/v1/Chassis/Node0/Sensors/ChassisVoltageRegulator6OutputVoltage",
    "@odata.type": "#Sensor.v1_1_0.Sensor",
    "Id": "ChassisVoltageRegulator6OutputVoltage",
    "Name": "48V->12V Converter",
    "Oem": {
        "Index": 6,
        "ParentalContext": "Chassis",
        "ReferenceDesignator": "VRM1"
    },
    "PhysicalContext": "VoltageRegulator",
    "PhysicalSubContext": "Output",
    "Reading": 11.898,
    "ReadingTime": "2024-04-04T14:12:14.905641097Z",
    "ReadingType": "Voltage",
    "ReadingUnits": "V"
}