{
    "@odata.id": "/redfish/v1/Systems/system/LogServices/PostCodes/Entries/B25-400",
    "@odata.type": "#LogEntry.v1_12_0.LogEntry",
    "AdditionalDataURI": "/redfish/v1/Systems/system/LogServices/PostCodes/Entries/B25-400/attachment",
    "Created": "2023-11-28T13:27:04+00:00",
    "EntryType": "Event",
    "Id": "B25-400",
    "Message": "Boot Count: 25; Time Stamp Offset: 72165.1436 seconds; POST Code: 0x010000000180050300",
    "MessageArgs": [
        "25",
        "72165.1436",
        "0x010000000180050300"
    ],
    "MessageId": "OpenBMC.0.2.BIOSPOSTCode",
    "Name": "POST Code Log Entry",
    "Severity": "OK"
}