{
    "@odata.id": "/redfish/v1/Systems/system/LogServices/PostCodes/Entries/B29-117",
    "@odata.type": "#LogEntry.v1_12_0.LogEntry",
    "AdditionalDataURI": "/redfish/v1/Systems/system/LogServices/PostCodes/Entries/B29-117/attachment",
    "Created": "2023-10-25T06:40:28+00:00",
    "EntryType": "Event",
    "Id": "B29-117",
    "Message": "Boot Count: 29; Time Stamp Offset: 54.0443 seconds; POST Code: 0x010000000000020200",
    "MessageArgs": [
        "29",
        "54.0443",
        "0x010000000000020200"
    ],
    "MessageId": "OpenBMC.0.2.BIOSPOSTCode",
    "Name": "POST Code Log Entry",
    "Severity": "OK"
}