{
    "@odata.id": "/redfish/v1/Systems/system/LogServices/PostCodes/Entries/B25-331",
    "@odata.type": "#LogEntry.v1_12_0.LogEntry",
    "AdditionalDataURI": "/redfish/v1/Systems/system/LogServices/PostCodes/Entries/B25-331/attachment",
    "Created": "2023-11-28T13:26:33+00:00",
    "EntryType": "Event",
    "Id": "B25-331",
    "Message": "Boot Count: 25; Time Stamp Offset: 72134.6700 seconds; POST Code: 0x01000000020002c100",
    "MessageArgs": [
        "25",
        "72134.6700",
        "0x01000000020002c100"
    ],
    "MessageId": "OpenBMC.0.2.BIOSPOSTCode",
    "Name": "POST Code Log Entry",
    "Severity": "OK"
}