{
    "@odata.etag": "W/\"1646685118\"",
    "@odata.id": "/redfish/v1/Chassis/CDU/Sensors/CoolingSubsystemMotor2Energy",
    "@odata.type": "#Sensor.v1_1_0.Sensor",
    "Id": "CoolingSubsystemMotor2Energy",
    "Name": "VFD2 Run-Time Energy Counter",
    "Oem": {
        "Index": 2,
        "ParentalContext": "CoolingSubsystem"
    },
    "PhysicalContext": "Motor",
    "Reading": 6556,
    "ReadingTime": "2022-03-11T21:43:44.009015946Z",
    "ReadingType": "EnergyJoules",
    "ReadingUnits": "J"
}