{
    "@odata.id": "/redfish/v1/Systems/system/LogServices/PostCodes/Entries/B23-79",
    "@odata.type": "#LogEntry.v1_12_0.LogEntry",
    "AdditionalDataURI": "/redfish/v1/Systems/system/LogServices/PostCodes/Entries/B23-79/attachment",
    "Created": "2023-12-05T15:42:35+00:00",
    "EntryType": "Event",
    "Id": "B23-79",
    "Message": "Boot Count: 23; Time Stamp Offset: 25.1709 seconds; POST Code: 0x010000000000010200",
    "MessageArgs": [
        "23",
        "25.1709",
        "0x010000000000010200"
    ],
    "MessageId": "OpenBMC.0.2.BIOSPOSTCode",
    "Name": "POST Code Log Entry",
    "Severity": "OK"
}