{
    "@odata.etag": "W/\"1646765171\"",
    "@odata.id": "/redfish/v1/Managers/BMC/NetworkProtocol/HTTPS/Certificates/1",
    "Certificate": "Certificate:\n    Data:\n        Version: 3 (0x2)\n        Serial Number: 1 (0x1)\n        Signature Algorithm: sha256WithRSAEncryption\n        Issuer: C=XX, ST=XX, L=XX, O=XX, OU=XX, CN=x9000c1s0b0-CA\n        Validity\n            Not Before: Mar  7 20:37:01 2022 GMT\n            Not After : Mar  4 20:37:01 2032 GMT\n        Subject: C=XX, ST=XX, O=XX, OU=XX, CN=x9000c1s0b0\n        Subject Public Key Info:\n            Public Key Algorithm: rsaEncryption\n                RSA Public-Key: (1024 bit)\n                Modulus:\n                    00:d5:3c:37:8c:eb:bd:2d:9e:32:6f:80:35:15:8b:\n                    bb:f3:74:21:77:65:ef:6d:51:3a:ae:b7:f8:b4:ba:\n                    e1:b6:04:b9:96:de:37:01:0c:43:36:43:91:43:c1:\n                    aa:ca:50:f9:a8:1d:96:e8:39:ff:b4:99:d9:87:a5:\n                    6a:65:5c:08:e2:61:bb:d2:8c:8c:04:b2:5d:7e:e9:\n                    10:63:69:f4:59:4e:b9:d4:d3:33:83:6e:79:20:f8:\n                    21:ae:6d:c3:e3:fa:e4:05:d3:35:89:5c:c5:06:a0:\n                    8f:a2:27:d1:f4:76:d2:b6:fb:9c:0d:1c:5b:55:7b:\n                    d3:11:9f:97:5c:e9:2f:88:15\n                Exponent: 65537 (0x10001)\n        X509v3 extensions:\n            X509v3 Basic Constraints: \n                CA:FALSE\n            X509v3 Subject Key Identifier: \n                28:D0:33:AA:A9:A0:1F:60:74:F7:8B:CA:E5:38:03:03:51:7E:F4:71\n            X509v3 Authority Key Identifier: \n                keyid:1B:BC:6F:19:35:EF:31:EA:78:0B:EA:64:0A:94:9F:B8:44:90:C9:5C\n\n            X509v3 Subject Alternative Name: \n                DNS:x9000c1s0b0\n    Signature Algorithm: sha256WithRSAEncryption\n         4d:74:36:d7:62:69:0f:97:01:f4:63:57:67:c6:c9:a2:f7:e0:\n         4d:29:00:46:74:07:a6:ce:50:d5:50:00:56:39:29:6c:ab:0a:\n         0e:f5:a4:37:c7:a9:3e:0e:07:62:dc:d0:54:a3:2d:10:a2:c5:\n         de:ff:5b:15:5d:3f:f5:bc:00:eb:6f:fa:b8:6a:61:64:1a:55:\n         8b:3f:a8:7a:31:ad:1c:94:29:2b:38:3e:3a:f7:af:da:16:03:\n         50:49:21:8e:d6:79:7e:d0:7e:d2:09:ae:b4:6f:c7:80:b9:4d:\n         10:5d:14:22:37:9e:c6:4d:44:3b:a6:22:fb:2e:2f:94:ff:d0:\n         ca:35\n-----BEGIN CERTIFICATE-----\nMIICfzCCAeigAwIBAgIBATANBgkqhkiG9w0BAQsFADBaMQswCQYDVQQGEwJYWDEL\nMAkGA1UECAwCWFgxCzAJBgNVBAcMAlhYMQswCQYDVQQKDAJYWDELMAkGA1UECwwC\nWFgxFzAVBgNVBAMMDng5MDAwYzFzMGIwLUNBMB4XDTIyMDMwNzIwMzcwMVoXDTMy\nMDMwNDIwMzcwMVowSjELMAkGA1UEBhMCWFgxCzAJBgNVBAgMAlhYMQswCQYDVQQK\nDAJYWDELMAkGA1UECwwCWFgxFDASBgNVBAMMC3g5MDAwYzFzMGIwMIGfMA0GCSqG\nSIb3DQEBAQUAA4GNADCBiQKBgQDVPDeM670tnjJvgDUVi7vzdCF3Ze9tUTqut/i0\nuuG2BLmW3jcBDEM2Q5FDwarKUPmoHZboOf+0mdmHpWplXAjiYbvSjIwEsl1+6RBj\nafRZTrnU0zODbnkg+CGubcPj+uQF0zWJXMUGoI+iJ9H0dtK2+5wNHFtVe9MRn5dc\n6S+IFQIDAQABo2UwYzAJBgNVHRMEAjAAMB0GA1UdDgQWBBQo0DOqqaAfYHT3i8rl\nOAMDUX70cTAfBgNVHSMEGDAWgBQbvG8ZNe8x6ngL6mQKlJ+4RJDJXDAWBgNVHREE\nDzANggt4OTAwMGMxczBiMDANBgkqhkiG9w0BAQsFAAOBgQBNdDbXYmkPlwH0Y1dn\nxsmi9+BNKQBGdAemzlDVUABWOSlsqwoO9aQ3x6k+Dgdi3NBUoy0QosXe/1sVXT/1\nvADrb/q4amFkGlWLP6h6Ma0clCkrOD4696/aFgNQSSGO1nl+0H7SCa60b8eAuU0Q\nXRQiN57GTUQ7piL7Li+U/9DKNQ==\n-----END CERTIFICATE-----\n",
    "Description": "Certificate Details",
    "KeyUsage": "ServerAuthentication",
    "Name": "Certificate"
}