{
    "@odata.id": "/redfish/v1/Systems/system/LogServices/PostCodes/Entries/B29-27",
    "@odata.type": "#LogEntry.v1_12_0.LogEntry",
    "AdditionalDataURI": "/redfish/v1/Systems/system/LogServices/PostCodes/Entries/B29-27/attachment",
    "Created": "2023-10-25T06:39:34+00:00",
    "EntryType": "Event",
    "Id": "B29-27",
    "Message": "Boot Count: 29; Time Stamp Offset: 0.9108 seconds; POST Code: 0x01000000000002c004",
    "MessageArgs": [
        "29",
        "0.9108",
        "0x01000000000002c004"
    ],
    "MessageId": "OpenBMC.0.2.BIOSPOSTCode",
    "Name": "POST Code Log Entry",
    "Severity": "OK"
}