{
    "@odata.id": "/redfish/v1/Systems/system/LogServices/PostCodes/Entries/B20-59",
    "@odata.type": "#LogEntry.v1_12_0.LogEntry",
    "AdditionalDataURI": "/redfish/v1/Systems/system/LogServices/PostCodes/Entries/B20-59/attachment",
    "Created": "2024-02-08T19:42:45+00:00",
    "EntryType": "Event",
    "Id": "B20-59",
    "Message": "Boot Count: 20; Time Stamp Offset: 78.3492 seconds; POST Code: 0x010000000080050300",
    "MessageArgs": [
        "20",
        "78.3492",
        "0x010000000080050300"
    ],
    "MessageId": "OpenBMC.0.2.BIOSPOSTCode",
    "Name": "POST Code Log Entry",
    "Severity": "OK"
}