{
    "@odata.id": "/redfish/v1/Systems/system/LogServices/PostCodes/Entries/B23-70",
    "@odata.type": "#LogEntry.v1_12_0.LogEntry",
    "AdditionalDataURI": "/redfish/v1/Systems/system/LogServices/PostCodes/Entries/B23-70/attachment",
    "Created": "2024-02-05T15:48:02+00:00",
    "EntryType": "Event",
    "Id": "B23-70",
    "Message": "Boot Count: 23; Time Stamp Offset: 222.7432 seconds; POST Code: 0x01000000000001c000",
    "MessageArgs": [
        "23",
        "222.7432",
        "0x01000000000001c000"
    ],
    "MessageId": "OpenBMC.0.2.BIOSPOSTCode",
    "Name": "POST Code Log Entry",
    "Severity": "OK"
}