{
    "@odata.id": "/redfish/v1/Systems/system/LogServices/PostCodes/Entries/B23-72",
    "@odata.type": "#LogEntry.v1_12_0.LogEntry",
    "AdditionalDataURI": "/redfish/v1/Systems/system/LogServices/PostCodes/Entries/B23-72/attachment",
    "Created": "2024-02-05T15:48:02+00:00",
    "EntryType": "Event",
    "Id": "B23-72",
    "Message": "Boot Count: 23; Time Stamp Offset: 222.9170 seconds; POST Code: 0x01000000000002c040",
    "MessageArgs": [
        "23",
        "222.9170",
        "0x01000000000002c040"
    ],
    "MessageId": "OpenBMC.0.2.BIOSPOSTCode",
    "Name": "POST Code Log Entry",
    "Severity": "OK"
}