{
    "@odata.id": "/redfish/v1/Managers/BMC_0/LogServices/EventLog/Entries/1701300109_1",
    "@odata.type": "#LogEntry.v1_12_0.LogEntry",
    "Created": "2023-11-29T23:21:49+00:00",
    "EntryType": "Event",
    "EventId": "dca898e2-b990-4441-86f4-74092a7650a0",
    "Id": "1701300109_1",
    "Message": "The requested resource of type #Manager.v1_11_0.Manager named 'Self' was not found.",
    "MessageArgs": [
        "#Manager.v1_11_0.Manager",
        "Self"
    ],
    "MessageId": "Base.1.11.ResourceNotFound",
    "Name": "Log Entry 1701300109_1",
    "Severity": "Critical"
}