{
    "@odata.id": "/redfish/v1/Systems/system/LogServices/PostCodes/Entries/B23-65",
    "@odata.type": "#LogEntry.v1_12_0.LogEntry",
    "AdditionalDataURI": "/redfish/v1/Systems/system/LogServices/PostCodes/Entries/B23-65/attachment",
    "Created": "2024-02-05T15:48:01+00:00",
    "EntryType": "Event",
    "Id": "B23-65",
    "Message": "Boot Count: 23; Time Stamp Offset: 222.4638 seconds; POST Code: 0x01000000010001c100",
    "MessageArgs": [
        "23",
        "222.4638",
        "0x01000000010001c100"
    ],
    "MessageId": "OpenBMC.0.2.BIOSPOSTCode",
    "Name": "POST Code Log Entry",
    "Severity": "OK"
}