{
    "@odata.etag": "W/\"947411862\"",
    "@odata.id": "/redfish/v1/Chassis/Node0/Sensors/Accelerator1VoltageRegulator10MaximumOutputVoltage",
    "@odata.type": "#Sensor.v1_1_0.Sensor",
    "ElectricalContext": "Maximum",
    "Id": "Accelerator1VoltageRegulator10MaximumOutputVoltage",
    "Name": "VDDCR_VDD1",
    "Oem": {
        "Index": 10,
        "ParentalContext": "Accelerator",
        "ParentalIndex": 1,
        "ReferenceDesignator": "U6068"
    },
    "PhysicalContext": "VoltageRegulator",
    "PhysicalSubContext": "Output",
    "Reading": 0.8225,
    "ReadingTime": "2000-01-09T09:58:06.309899040Z",
    "ReadingType": "Voltage",
    "ReadingUnits": "V",
    "Thresholds": {
        "UpperFatal": {
            "Activation": "Increasing",
            "Reading": 1.76
        }
    }
}