{
    "@odata.id": "/redfish/v1/Systems/system/LogServices/PostCodes/Entries/B25-165",
    "@odata.type": "#LogEntry.v1_12_0.LogEntry",
    "AdditionalDataURI": "/redfish/v1/Systems/system/LogServices/PostCodes/Entries/B25-165/attachment",
    "Created": "2023-11-27T18:36:29+00:00",
    "EntryType": "Event",
    "Id": "B25-165",
    "Message": "Boot Count: 25; Time Stamp Offset: 4330.7467 seconds; POST Code: 0x010000000000020200",
    "MessageArgs": [
        "25",
        "4330.7467",
        "0x010000000000020200"
    ],
    "MessageId": "OpenBMC.0.2.BIOSPOSTCode",
    "Name": "POST Code Log Entry",
    "Severity": "OK"
}